LICENSE.md
README.md
setup.cfg
setup.py
isobar/__init__.py
isobar/chord.py
isobar/constants.py
isobar/exceptions.py
isobar/instrument.py
isobar/key.py
isobar/note.py
isobar/scale.py
isobar/util.py
isobar.egg-info/PKG-INFO
isobar.egg-info/SOURCES.txt
isobar.egg-info/dependency_links.txt
isobar.egg-info/requires.txt
isobar.egg-info/top_level.txt
isobar/effects/__init__.py
isobar/effects/note_effect.py
isobar/globals/__init__.py
isobar/globals/globals.py
isobar/globals/sync.py
isobar/io/__init__.py
isobar/io/midinote.py
isobar/io/output.py
isobar/io/cv/__init__.py
isobar/io/cv/output.py
isobar/io/dummy/__init__.py
isobar/io/dummy/output.py
isobar/io/fluidsynth/__init__.py
isobar/io/fluidsynth/output.py
isobar/io/midi/__init__.py
isobar/io/midi/input.py
isobar/io/midi/output.py
isobar/io/midifile/__init__.py
isobar/io/midifile/input.py
isobar/io/midifile/output.py
isobar/io/mpe/__init__.py
isobar/io/mpe/note.py
isobar/io/mpe/output.py
isobar/io/netclock/__init__.py
isobar/io/netclock/receiver.py
isobar/io/netclock/sender.py
isobar/io/netglobals/__init__.py
isobar/io/netglobals/receiver.py
isobar/io/netglobals/sender.py
isobar/io/osc/__init__.py
isobar/io/osc/output.py
isobar/io/signalflow/__init__.py
isobar/io/signalflow/output.py
isobar/io/socketio/__init__.py
isobar/io/socketio/output.py
isobar/io/supercollider/__init__.py
isobar/io/supercollider/output.py
isobar/notation/__init__.py
isobar/notation/notation.py
isobar/pattern/__init__.py
isobar/pattern/chance.py
isobar/pattern/core.py
isobar/pattern/fade.py
isobar/pattern/lsystem.py
isobar/pattern/markov.py
isobar/pattern/midi.py
isobar/pattern/monome.py
isobar/pattern/oscillator.py
isobar/pattern/scalar.py
isobar/pattern/sequence.py
isobar/pattern/static.py
isobar/pattern/tonal.py
isobar/pattern/warp.py
isobar/shorthand/__init__.py
isobar/shorthand/abbreviations.py
isobar/shorthand/patches.py
isobar/shorthand/setup.py
isobar/shorthand/sync.py
isobar/timelines/__init__.py
isobar/timelines/automation.py
isobar/timelines/clock.py
isobar/timelines/clock_link.py
isobar/timelines/lfo.py
isobar/timelines/midi_note.py
isobar/timelines/timeline.py
