Metadata-Version: 2.1
Name: isobar
Version: 0.2.1
Summary: A Python library to express and manipulate musical patterns
Home-page: https://github.com/ideoforms/isobar
Author: Daniel Jones
Author-email: dan-isobar@erase.net
Keywords: sound,music,composition
Classifier: Topic :: Multimedia :: Sound/Audio
Classifier: Topic :: Artistic Software
Classifier: Development Status :: 4 - Beta
Classifier: Intended Audience :: Developers
License-File: LICENSE.md
